{
	"info": {
		"_postman_id": "9aed6e94-0e55-4675-a267-877a051223e6",
		"name": "hngx2",
		"schema": "https://schema.getpostman.com/json/collection/v2.1.0/collection.json",
		"_exporter_id": "22888526"
	},
	"item": [
		{
			"name": "all  persons",
			"request": {
				"method": "GET",
				"header": [],
				"url": {
					"raw": "http://localhost:8000/api",
					"protocol": "http",
					"host": [
						"localhost"
					],
					"port": "8000",
					"path": [
						"api"
					]
				},
				"description": "To get all the database with everyone'e data"
			},
			"response": []
		},
		{
			"name": "Get one",
			"request": {
				"method": "GET",
				"header": [],
				"url": {
					"raw": "http://localhost:8000/api/65038b07043c91af6d669ea9",
					"protocol": "http",
					"host": [
						"localhost"
					],
					"port": "8000",
					"path": [
						"api",
						"65038b07043c91af6d669ea9"
					]
				}
			},
			"response": []
		},
		{
			"name": "Update one",
			"request": {
				"method": "PUT",
				"header": [],
				"body": {
					"mode": "raw",
					"raw": "{\r\n    \"name\":  \"David Rose\"\r\n}",
					"options": {
						"raw": {
							"language": "json"
						}
					}
				},
				"url": {
					"raw": "http://localhost:8000/api/6503896312b15ccc225fc0c2",
					"protocol": "http",
					"host": [
						"localhost"
					],
					"port": "8000",
					"path": [
						"api",
						"6503896312b15ccc225fc0c2"
					]
				}
			},
			"response": []
		},
		{
			"name": "Delete one",
			"request": {
				"method": "DELETE",
				"header": [],
				"url": {
					"raw": "http://localhost:8000/api/65038b07043c91af6d669ea9",
					"protocol": "http",
					"host": [
						"localhost"
					],
					"port": "8000",
					"path": [
						"api",
						"65038b07043c91af6d669ea9"
					],
					"query": [
						{
							"key": "id",
							"value": "123",
							"disabled": true
						}
					]
				}
			},
			"response": []
		},
		{
			"name": "Create person",
			"request": {
				"method": "POST",
				"header": [],
				"body": {
					"mode": "raw",
					"raw": "{\r\n    \"name\": \"David\"\r\n}",
					"options": {
						"raw": {
							"language": "json"
						}
					}
				},
				"url": {
					"raw": "http://localhost:8000/api",
					"protocol": "http",
					"host": [
						"localhost"
					],
					"port": "8000",
					"path": [
						"api"
					]
				}
			},
			"response": []
		}
	]
}